relworx/__init__.py
relworx/client.py
relworx/exceptions.py
relworx/py.typed
relworx-0.1.0.dist-info/licenses/LICENSE
relworx-0.1.0.dist-info/METADATA
relworx-0.1.0.dist-info/WHEEL
relworx-0.1.0.dist-info/top_level.txt
relworx-0.1.0.dist-info/RECORD
